xcm_wiki/__init__.py
xcm_wiki/__main__.py
xcm_wiki/cm.py
xcm_wiki/exceptions.py
xcm_wiki/log.conf
xcm_wiki_gen-0.1.3.dist-info/licenses/LICENSE
xcm_wiki_gen-0.1.3.dist-info/METADATA
xcm_wiki_gen-0.1.3.dist-info/WHEEL
xcm_wiki_gen-0.1.3.dist-info/entry_points.txt
xcm_wiki_gen-0.1.3.dist-info/top_level.txt
xcm_wiki_gen-0.1.3.dist-info/RECORD
