Metadata-Version: 2.4
Name: xcm-wiki-gen
Version: 0.1.3
Summary: Generates a set of GitHub Wiki class and relationship description template markdown files from an input xcm (executable class model) file.
Author-email: Leon Starr <leon_starr@modelint.com>
License: MIT License
Project-URL: repository, https://github.com/modelint/wikigen
Project-URL: documentation, https://github.com/modelint/wikigen/wiki
Keywords: action language,executable uml,mbse,xuml,xtuml,platform independent,sysml
Classifier: License :: OSI Approved :: MIT License
Classifier: Programming Language :: Python
Classifier: Programming Language :: Python :: 3
Requires-Python: >=3.13
License-File: LICENSE
Requires-Dist: xcm-parser
Requires-Dist: tomli; python_version < "3.11"
Provides-Extra: build
Requires-Dist: build; extra == "build"
Requires-Dist: twine; extra == "build"
Provides-Extra: dev
Requires-Dist: bump2version; extra == "dev"
Requires-Dist: pytest; extra == "dev"
Dynamic: license-file
